{"_type":"export","__export_format":4,"__export_date":"2023-01-11T15:30:18.761Z","__export_source":"insomnia.desktop.app:v2022.4.2","resources":[{"_id":"req_b01a7ead05374480959fe830c2d95253","parentId":"wrk_0c2816c5f1f14f9e8b69daa1a5783fef","modified":1673370676979,"created":1672113383208,"url":" {{ _.base_url }}","name":"Hello, world!","description":"","method":"GET","body":{},"parameters":[],"headers":[],"authentication":{},"metaSortKey":-1673326336272,"isPrivate":false,"settingStoreCookies":true,"settingSendCookies":true,"settingDisableRenderRequestBody":false,"settingEncodeUrl":true,"settingRebuildPath":true,"settingFollowRedirects":"global","_type":"request"},{"_id":"wrk_0c2816c5f1f14f9e8b69daa1a5783fef","parentId":null,"modified":1671764315778,"created":1671764315778,"name":"Food App","description":"","scope":"collection","_type":"workspace"},{"_id":"req_a011cc0d0b604373b1f50c956a737819","parentId":"fld_f77e009b5200440eb2766bdabe93e4ca","modified":1673449147847,"created":1673326340195,"url":"{{ _.base_url }}/api/v1/auth/login","name":"Login","description":"","method":"POST","body":{"mimeType":"application/json","text":"{\n\t\"email\": \"{{ _.email }}\",\n\t\"password\": \"password123\"\t\n}"},"parameters":[],"headers":[{"name":"Content-Type","value":"application/json","id":"pair_6ab368d2c0564d04beaa223e22603a28"}],"authentication":{},"metaSortKey":-1673326340195,"isPrivate":false,"settingStoreCookies":true,"settingSendCookies":true,"settingDisableRenderRequestBody":false,"settingEncodeUrl":true,"settingRebuildPath":true,"settingFollowRedirects":"global","_type":"request"},{"_id":"fld_f77e009b5200440eb2766bdabe93e4ca","parentId":"wrk_0c2816c5f1f14f9e8b69daa1a5783fef","modified":1673326336222,"created":1673326336222,"name":"Auth","description":"","environment":{},"environmentPropertyOrder":null,"metaSortKey":-1673326336222,"_type":"request_group"},{"_id":"req_2c29239d1537407fa58cb30f9a007826","parentId":"fld_6b76e8cf26bb4db09a76226368b8feda","modified":1673158464519,"created":1672115268678,"url":"{{ _.base_url }}/api/v1/user/{{ _.user_id }}","name":"Find by ID","description":"","method":"GET","body":{"mimeType":"multipart/form-data","params":[]},"parameters":[],"headers":[{"name":"Content-Type","value":"multipart/form-data","id":"pair_42df773b7f904c21a78458f5092de8ff"}],"authentication":{},"metaSortKey":-1673064593914,"isPrivate":false,"settingStoreCookies":true,"settingSendCookies":true,"settingDisableRenderRequestBody":false,"settingEncodeUrl":true,"settingRebuildPath":true,"settingFollowRedirects":"global","_type":"request"},{"_id":"fld_6b76e8cf26bb4db09a76226368b8feda","parentId":"wrk_0c2816c5f1f14f9e8b69daa1a5783fef","modified":1671764377586,"created":1671764377586,"name":"User","description":"","environment":{},"environmentPropertyOrder":null,"metaSortKey":-1671764377586,"_type":"request_group"},{"_id":"req_4bceb70c8cb84518963e5ce54ed0f52d","parentId":"fld_6b76e8cf26bb4db09a76226368b8feda","modified":1672164530100,"created":1671769665420,"url":"{{ _.base_url }}/api/v1/user/","name":"Find all users","description":"","method":"GET","body":{},"parameters":[],"headers":[],"authentication":{},"metaSortKey":-1672115268728,"isPrivate":false,"settingStoreCookies":true,"settingSendCookies":true,"settingDisableRenderRequestBody":false,"settingEncodeUrl":true,"settingRebuildPath":true,"settingFollowRedirects":"global","_type":"request"},{"_id":"req_3c7cfcf009214d269f9d9bdfe25c3059","parentId":"fld_6b76e8cf26bb4db09a76226368b8feda","modified":1673448954090,"created":1671764360193,"url":"{{ _.base_url }}/api/v1/user/","name":"Create user","description":"","method":"POST","body":{"mimeType":"application/json","text":"{\n\t\"name\": \"Adan Smith Three\",\n\t\"email\": \"{{ _.email }}\",\n\t\"password\": \"password123\",\n\t\"role\": \"ADMIN\"\n}\t"},"parameters":[],"headers":[{"name":"Content-Type","value":"application/json","id":"pair_6f9ac28cadb4451c8cad6d979a0784e6"}],"authentication":{},"metaSortKey":-1671942467049,"isPrivate":false,"settingStoreCookies":true,"settingSendCookies":true,"settingDisableRenderRequestBody":false,"settingEncodeUrl":true,"settingRebuildPath":true,"settingFollowRedirects":"global","_type":"request"},{"_id":"req_79f63566def44c3e9d28d08670159c16","parentId":"fld_6b76e8cf26bb4db09a76226368b8feda","modified":1673125040677,"created":1673050504332,"url":"{{ _.base_url }}/api/v1/user/verify/{{ _.user_id }}/{{ _.verification_code }}","name":"Verify User","description":"","method":"POST","body":{"mimeType":"application/json","text":""},"parameters":[{"id":"pair_e7d0d8951f914cbabc7a5b70515c5254","name":"","value":"","description":""}],"headers":[{"name":"Content-Type","value":"application/json"}],"authentication":{},"metaSortKey":-1671277603786,"isPrivate":false,"settingStoreCookies":true,"settingSendCookies":true,"settingDisableRenderRequestBody":false,"settingEncodeUrl":true,"settingRebuildPath":true,"settingFollowRedirects":"global","_type":"request"},{"_id":"req_63596c1bfe0744e88dc8d7aa3195326d","parentId":"fld_6b76e8cf26bb4db09a76226368b8feda","modified":1673449095732,"created":1673064593864,"url":"{{ _.base_url }}/api/v1/user/forgotpassword","name":"Forgot Password","description":"","method":"POST","body":{"mimeType":"application/json","text":"{\n\t\"email\": \"{{ _.email }}\"\n}"},"parameters":[],"headers":[{"name":"Content-Type","value":"application/json","id":"pair_bc8ea43871d04d7486da06215150e045"}],"authentication":{},"metaSortKey":-1671277603736,"isPrivate":false,"settingStoreCookies":true,"settingSendCookies":true,"settingDisableRenderRequestBody":false,"settingEncodeUrl":true,"settingRebuildPath":true,"settingFollowRedirects":"global","_type":"request"},{"_id":"req_8792ebd84735431b80dd520ef0537f9f","parentId":"fld_6b76e8cf26bb4db09a76226368b8feda","modified":1673449102838,"created":1673129852586,"url":"{{ _.base_url }}/api/v1/user/resetpassword/{{ _.user_id }}/{{ _.password_reset_code }}","name":"Reset Password","description":"","method":"POST","body":{"mimeType":"application/json","text":"{\n\t\"password\": \"{{ _.new_password }}\",\n\t\"passwordConfirmation\": \"{{ _.new_password }}\"\n}"},"parameters":[],"headers":[{"name":"Content-Type","value":"application/json","id":"pair_bc8ea43871d04d7486da06215150e045"}],"authentication":{},"metaSortKey":-1670945172129.5,"isPrivate":false,"settingStoreCookies":true,"settingSendCookies":true,"settingDisableRenderRequestBody":false,"settingEncodeUrl":true,"settingRebuildPath":true,"settingFollowRedirects":"global","_type":"request"},{"_id":"req_12618be03dee448b842cc26fdf480885","parentId":"fld_243f9b2d8e6f47afb6ffa10d77691fb8","modified":1673449196747,"created":1673370691038,"url":"{{ _.base_url }}/api/v1/profile","name":"User Profile","description":"","method":"GET","body":{},"parameters":[],"headers":[],"authentication":{"type":"bearer","token":"{{ _.access_token }}","disabled":false},"metaSortKey":-1671764377511,"isPrivate":false,"settingStoreCookies":true,"settingSendCookies":true,"settingDisableRenderRequestBody":false,"settingEncodeUrl":true,"settingRebuildPath":true,"settingFollowRedirects":"global","_type":"request"},{"_id":"fld_243f9b2d8e6f47afb6ffa10d77691fb8","parentId":"wrk_0c2816c5f1f14f9e8b69daa1a5783fef","modified":1673370711557,"created":1673370686785,"name":"Profile","description":"","environment":{},"environmentPropertyOrder":null,"metaSortKey":-1671764377536,"_type":"request_group"},{"_id":"env_8dadaaf0ec5c874105c5432793b646e29528685a","parentId":"wrk_0c2816c5f1f14f9e8b69daa1a5783fef","modified":1673418702835,"created":1671764315808,"name":"Base Environment","data":{"base_url":"http://localhost:3000","email":"adam_smith3@mail.com","user_id":"{% response 'body', 'req_3c7cfcf009214d269f9d9bdfe25c3059', 'b64::JC5kYXRhW2lkXQ==::46b', 'never', 60 %}","verification_code":"{% response 'body', 'req_3c7cfcf009214d269f9d9bdfe25c3059', 'b64::JC5kYXRhW3ZlcmlmaWNhdGlvbkNvZGVd::46b', 'never', 60 %}","password_reset_code":"NTXqMWy_Adc4z4zaJg2XL","new_password":"vimuser123","access_token":"{% response 'body', 'req_a011cc0d0b604373b1f50c956a737819', 'b64::JC5kYXRhW2FjY2Vzc1Rva2VuXQ==::46b', 'never', 60 %}","refresh_token":"{% response 'body', 'req_a011cc0d0b604373b1f50c956a737819', 'b64::JC5kYXRhW3JlZnJlc2hUb2tlbl0=::46b', 'never', 60 %}"},"dataPropertyOrder":{"&":["base_url","email","user_id","verification_code","password_reset_code","new_password","access_token","refresh_token"]},"color":null,"isPrivate":false,"metaSortKey":1671764315808,"_type":"environment"},{"_id":"jar_8dadaaf0ec5c874105c5432793b646e29528685a","parentId":"wrk_0c2816c5f1f14f9e8b69daa1a5783fef","modified":1671764315811,"created":1671764315811,"name":"Default Jar","cookies":[],"_type":"cookie_jar"},{"_id":"spc_2d608d1e2a6f4e048d5360848b69ebce","parentId":"wrk_0c2816c5f1f14f9e8b69daa1a5783fef","modified":1671764315793,"created":1671764315793,"fileName":"Food App","contents":"","contentType":"yaml","_type":"api_spec"},{"_id":"env_35d19a26ef0e48a4a47c71867220bd13","parentId":"env_8dadaaf0ec5c874105c5432793b646e29528685a","modified":1673327218015,"created":1673327207373,"name":"Test one","data":{},"dataPropertyOrder":{},"color":null,"isPrivate":false,"metaSortKey":1673327207373,"_type":"environment"}]}